instruct_qa/__init__.py
instruct_qa/experiment_utils.py
instruct_qa/response_runner.py
instruct_qa/version.py
instruct_qa/collections/__init__.py
instruct_qa/collections/dpr_wiki_collection.py
instruct_qa/collections/faithdial_collection.py
instruct_qa/collections/hotpot_wiki_collection.py
instruct_qa/collections/topiocqa_wiki_collection.py
instruct_qa/collections/utils.py
instruct_qa/dataset/__init__.py
instruct_qa/dataset/dataset.py
instruct_qa/dataset/utils.py
instruct_qa/dataset/convqa/__init__.py
instruct_qa/dataset/convqa/faithdial.py
instruct_qa/dataset/convqa/topiocqa.py
instruct_qa/dataset/qa/__init__.py
instruct_qa/dataset/qa/generic_qa.py
instruct_qa/dataset/qa/hotpot_qa.py
instruct_qa/dataset/qa/natural_questions.py
instruct_qa/evaluation/__init__.py
instruct_qa/evaluation/faithfulness_metrics.py
instruct_qa/evaluation/metrics.py
instruct_qa/evaluation/utils.py
instruct_qa/generation/__init__.py
instruct_qa/generation/generator.py
instruct_qa/generation/utils.py
instruct_qa/prompt/__init__.py
instruct_qa/prompt/templates.py
instruct_qa/prompt/utils.py
instruct_qa/retrieval/__init__.py
instruct_qa/retrieval/index.py
instruct_qa/retrieval/pyserini_utils.py
instruct_qa/retrieval/utils.py
instruct_qa-0.0.2.dist-info/LICENSE
instruct_qa-0.0.2.dist-info/METADATA
instruct_qa-0.0.2.dist-info/WHEEL
instruct_qa-0.0.2.dist-info/top_level.txt
instruct_qa-0.0.2.dist-info/RECORD
