Metadata-Version: 2.1
Name: instruct-qa
Version: 0.0.2
Summary: Empirical evaluation of retrieval-augmented instruction-following models.
Home-page: https://github.com/McGill-NLP/instruct-qa
Author: McGill NLP
License: UNKNOWN
Platform: UNKNOWN
Classifier: Programming Language :: Python :: 3
Classifier: Operating System :: OS Independent
Classifier: License :: OSI Approved :: Apache Software License
Requires-Python: >=3.7
Requires-Dist: torch
Requires-Dist: transformers
Requires-Dist: datasets
Requires-Dist: evaluate
Requires-Dist: wget
Requires-Dist: nltk
Requires-Dist: rouge-score
Requires-Dist: faiss-cpu
Requires-Dist: sentence-transformers
Requires-Dist: pyserini
Requires-Dist: flask
Requires-Dist: gunicorn
Requires-Dist: openai
Requires-Dist: accelerate
Requires-Dist: jsonlines
Requires-Dist: protobuf ==3.20.*
Provides-Extra: evaluation
Requires-Dist: tensorflow-text ; extra == 'evaluation'
Requires-Dist: bert-score ; extra == 'evaluation'
Requires-Dist: allennlp ; extra == 'evaluation'
Requires-Dist: allennlp-models ; extra == 'evaluation'
